pyskeleton/__init__.py
pyskeleton/__main__.py
pyskeleton/pyskeleton.tar.gz
pyskeleton-1.0.0.dist-info/LICENSE
pyskeleton-1.0.0.dist-info/METADATA
pyskeleton-1.0.0.dist-info/WHEEL
pyskeleton-1.0.0.dist-info/entry_points.txt
pyskeleton-1.0.0.dist-info/top_level.txt
pyskeleton-1.0.0.dist-info/RECORD
