Metadata-Version: 2.1
Name: pyskeleton
Version: 1.0.0
Summary: quickly create a python module.
Home-page: https://github.com/a358003542/pyskeleton
Author: wanze
Author-email: a358003542@outlook.com
Maintainer: wanze
Maintainer-email: a358003542@outlook.com
License: MIT
Keywords: skeleton,python
Platform: UNKNOWN
Classifier: License :: OSI Approved :: MIT License
Classifier: Operating System :: Microsoft
Classifier: Operating System :: POSIX :: Linux
Classifier: Programming Language :: Python :: 3
License-File: LICENSE
